short_text_analyzer/__init__.py
short_text_analyzer/_nbdev.py
short_text_analyzer/core.py
short_text_analyzer-0.1.dist-info/LICENSE
short_text_analyzer-0.1.dist-info/METADATA
short_text_analyzer-0.1.dist-info/WHEEL
short_text_analyzer-0.1.dist-info/entry_points.txt
short_text_analyzer-0.1.dist-info/top_level.txt
short_text_analyzer-0.1.dist-info/RECORD
