Metadata-Version: 2.1
Name: short-text-analyzer
Version: 0.1
Summary: This Short-Text Analyzer is created to help analyze the open-ended survey response which usually has less than three sentences. The analysis includes topic modeling, sentiment analysis, and visualization.
Home-page: https://github.com/thisisphume/short_text_analyzer/tree/master/
Author: Phume Ngampornsukswadi
Author-email: thisisphume@gmail.com
License: Apache Software License 2.0
Keywords: BERT NLP short-text topic-modeling clustering
Platform: UNKNOWN
Classifier: Development Status :: 3 - Alpha
Classifier: Intended Audience :: Developers
Classifier: License :: OSI Approved :: Apache Software License
Classifier: Natural Language :: English
Classifier: Programming Language :: Python :: 3.6
Classifier: Programming Language :: Python :: 3.7
Classifier: Programming Language :: Python :: 3.8
Requires-Python: >=3.6
